sharding/__init__.py
sharding/contracts/__init__.py
sharding/contracts/sharding_manager.json
sharding/contracts/sharding_manager.v.py
sharding/contracts/utils/__init__.py
sharding/contracts/utils/config.py
sharding/contracts/utils/smc_utils.py
sharding/handler/__init__.py
sharding/handler/exceptions.py
sharding/handler/log_handler.py
sharding/handler/shard_tracker.py
sharding/handler/smc_handler.py
sharding/handler/utils/__init__.py
sharding/handler/utils/log_parser.py
sharding/handler/utils/shard_tracker_utils.py
sharding/handler/utils/smc_handler_utils.py
sharding/handler/utils/web3_utils.py
sharding-0.0.2a2.dist-info/METADATA
sharding-0.0.2a2.dist-info/RECORD
sharding-0.0.2a2.dist-info/WHEEL
sharding-0.0.2a2.dist-info/top_level.txt
